[{"calorie":0.0,"count":0,"distance":0.0,"speed":0.0},{"calorie":0.0,"count":0,"distance":0.0,"speed":0.0},{"calorie":0.0,"count":0,"distance":0.0,"speed":0.0},{"calorie":0.0,"count":0,"distance":0.0,"speed":0.0},{"calorie":0.0,"count":0,"distance":0.0,"speed":0.0},{"calorie":0.0,"count":0,"distance":0.0,"speed":0.0},{"calorie":0.0,"count":0,"distance":0.0,"speed":0.0},{"calorie":0.0,"count":0,"distance":0.0,"speed":0.0},{"calorie":0.0,"count":0,"distance":0.0,"speed":0.0},{"calorie":0.0,"count":0,"distance":0.0,"speed":0.0},{"calorie":0.0,"count":0,"distance":0.0,"speed":0.0},{"calorie":0.0,"count":0,"distance":0.0,"speed":0.0},{"calorie":0.0,"count":0,"distance":0.0,"speed":0.0},{"calorie":0.0,"count":0,"distance":0.0,"speed":0.0},{"calorie":0.0,"count":0,"distance":0.0,"speed":0.0},{"calorie":0.0,"count":0,"distance":0.0,"speed":0.0},{"calorie":0.0,"count":0,"distance":0.0,"speed":0.0},{"calorie":0.0,"count":0,"distance":0.0,"speed":0.0},{"calorie":0.0,"count":0,"distance":0.0,"speed":0.0},{"calorie":0.0,"count":0,"distance":0.0,"speed":0.0},{"calorie":0.0,"count":0,"distance":0.0,"speed":0.0},{"calorie":0.0,"count":0,"distance":0.0,"speed":0.0},{"calorie":0.0,"count":0,"distance":0.0,"speed":0.0},{"calorie":0.0,"count":0,"distance":0.0,"speed":0.0},{"calorie":0.0,"count":0,"distance":0.0,"speed":0.0},{"calorie":0.0,"count":0,"distance":0.0,"speed":0.0},{"calorie":0.0,"count":0,"distance":0.0,"speed":0.0},{"calorie":0.0,"count":0,"distance":0.0,"speed":0.0},{"calorie":0.0,"count":0,"distance":0.0,"speed":0.0},{"calorie":0.0,"count":0,"distance":0.0,"speed":0.0},{"calorie":0.0,"count":0,"distance":0.0,"speed":0.0},{"calorie":0.0,"count":0,"distance":0.0,"speed":0.0},{"calorie":0.0,"count":0,"distance":0.0,"speed":0.0},{"calorie":0.0,"count":0,"distance":0.0,"speed":0.0},{"calorie":0.0,"count":0,"distance":0.0,"speed":0.0},{"calorie":0.0,"count":0,"distance":0.0,"speed":0.0},{"calorie":0.0,"count":0,"distance":0.0,"speed":0.0},{"calorie":0.0,"count":0,"distance":0.0,"speed":0.0},{"calorie":0.0,"count":0,"distance":0.0,"speed":0.0},{"calorie":0.0,"count":0,"distance":0.0,"speed":0.0},{"calorie":0.0,"count":0,"distance":0.0,"speed":0.0},{"calorie":0.0,"count":0,"distance":0.0,"speed":0.0},{"calorie":0.0,"count":0,"distance":0.0,"speed":0.0},{"calorie":0.0,"count":0,"distance":0.0,"speed":0.0},{"calorie":0.0,"count":0,"distance":0.0,"speed":0.0},{"calorie":0.0,"count":0,"distance":0.0,"speed":0.0},{"calorie":4.929999947547913,"count":133,"distance":99.0600004196167,"speed":4.518467903137207},{"calorie":6.050000101327896,"count":169,"distance":127.6399974822998,"speed":4.920217990875244},{"calorie":0.0,"count":0,"distance":0.0,"speed":0.0},{"calorie":0.550000011920929,"count":16,"distance":12.569999694824219,"speed":5.800000190734863},{"calorie":3.60999995470047,"count":98,"distance":72.23000144958496,"speed":4.277013301849365},{"calorie":8.999999940395355,"count":237,"distance":175.67000007629395,"speed":4.454633712768555},{"calorie":0.0,"count":0,"distance":0.0,"speed":0.0},{"calorie":0.0,"count":0,"distance":0.0,"speed":0.0},{"calorie":7.5799999833106995,"count":207,"distance":154.72000360488892,"speed":4.4767656326293945},{"calorie":6.1900001764297485,"count":160,"distance":118.67000198364258,"speed":4.4532880783081055},{"calorie":12.149999976158142,"count":334,"distance":248.42000198364258,"speed":4.481359481811523},{"calorie":24.46999990940094,"count":633,"distance":470.5299940109253,"speed":4.462160587310791},{"calorie":17.76000038534403,"count":480,"distance":360.70999360084534,"speed":4.665165901184082},{"calorie":3.880000114440918,"count":105,"distance":78.68999862670898,"speed":4.7285075187683105},{"calorie":0.0,"count":0,"distance":0.0,"speed":0.0},{"calorie":3.409999966621399,"count":90,"distance":67.05000114440918,"speed":4.376707077026367},{"calorie":18.040000200271606,"count":483,"distance":360.6899948120117,"speed":4.605356693267822},{"calorie":15.33000011742115,"count":406,"distance":305.32000374794006,"speed":4.572321891784668},{"calorie":11.490000128746033,"count":298,"distance":220.8900032043457,"speed":4.376002311706543},{"calorie":0.0,"count":0,"distance":0.0,"speed":0.0},{"calorie":10.460000038146973,"count":282,"distance":213.52999877929688,"speed":4.904416561126709},{"calorie":18.369999766349792,"count":484,"distance":362.23000049591064,"speed":4.697440147399902},{"calorie":13.26999980211258,"count":347,"distance":258.1999969482422,"speed":4.356241703033447},{"calorie":0.0,"count":0,"distance":0.0,"speed":0.0},{"calorie":20.789999961853027,"count":546,"distance":407.1999969482422,"speed":4.498180866241455},{"calorie":13.350000068545341,"count":359,"distance":268.83999967575073,"speed":4.538541793823242},{"calorie":12.359999895095825,"count":336,"distance":254.1699981689453,"speed":4.7592244148254395},{"calorie":0.0,"count":0,"distance":0.0,"speed":0.0},{"calorie":1.1799999475479126,"count":32,"distance":23.729999542236328,"speed":4.299999713897705},{"calorie":11.669999897480011,"count":313,"distance":234.830002784729,"speed":4.3834919929504395},{"calorie":13.51000002026558,"count":355,"distance":263.4900016784668,"speed":4.474278450012207},{"calorie":7.689999938011169,"count":210,"distance":157.83000087738037,"speed":4.5908894538879395},{"calorie":5.409999430179596,"count":147,"distance":111.96999311447144,"speed":4.900007247924805},{"calorie":2.7799999713897705,"count":73,"distance":54.42999839782715,"speed":4.427309513092041},{"calorie":0.9800000190734863,"count":26,"distance":19.6299991607666,"speed":4.900000095367432},{"calorie":20.599999845027924,"count":576,"distance":437.96000480651855,"speed":4.916873455047607},{"calorie":26.339999675750732,"count":732,"distance":555.0199947357178,"speed":4.852049827575684},{"calorie":21.489999890327454,"count":580,"distance":434.9600009918213,"speed":4.622313976287842},{"calorie":14.730000048875809,"count":421,"distance":320.97000074386597,"speed":5.005438804626465},{"calorie":11.73999798297882,"count":336,"distance":254.9099998474121,"speed":4.941126346588135},{"calorie":12.03000009059906,"count":322,"distance":241.52000045776367,"speed":4.566980838775635},{"calorie":4.65999960899353,"count":124,"distance":95.94000244140625,"speed":4.9084553718566895},{"calorie":4.770000129938126,"count":133,"distance":100.28999948501587,"speed":4.697299480438232},{"calorie":14.92999991774559,"count":410,"distance":307.08000326156616,"speed":4.738903045654297},{"calorie":19.81000006198883,"count":530,"distance":396.69000244140625,"speed":4.716803073883057},{"calorie":8.310000091791153,"count":222,"distance":166.8300004005432,"speed":4.766173839569092},{"calorie":5.199999928474426,"count":148,"distance":111.0200023651123,"speed":4.8883819580078125},{"calorie":15.01000002026558,"count":412,"distance":310.43999671936035,"speed":4.773953914642334},{"calorie":16.089999794960022,"count":440,"distance":329.7700004577637,"speed":4.694048881530762},{"calorie":4.199999630451202,"count":114,"distance":86.12999248504639,"speed":4.731803894042969},{"calorie":2.2800000309944153,"count":58,"distance":44.3799991607666,"speed":4.557281970977783},{"calorie":6.069999858736992,"count":163,"distance":120.59999942779541,"speed":4.397359848022461},{"calorie":2.709999978542328,"count":74,"distance":55.329999923706055,"speed":4.633228302001953},{"calorie":0.0,"count":0,"distance":0.0,"speed":0.0},{"calorie":1.8700000047683716,"count":56,"distance":42.810001373291016,"speed":5.199999809265137},{"calorie":0.0,"count":0,"distance":0.0,"speed":0.0},{"calorie":1.2599998712539673,"count":35,"distance":25.799999237060547,"speed":4.62717342376709},{"calorie":4.07999986410141,"count":106,"distance":78.89999961853027,"speed":4.448343276977539},{"calorie":2.0100000202655792,"count":53,"distance":38.440001010894775,"speed":4.085691452026367},{"calorie":0.0,"count":0,"distance":0.0,"speed":0.0},{"calorie":1.4999999701976776,"count":41,"distance":31.180001258850098,"speed":4.494672775268555},{"calorie":0.0,"count":0,"distance":0.0,"speed":0.0},{"calorie":4.620000034570694,"count":125,"distance":92.91999912261963,"speed":4.496101379394531},{"calorie":0.9100000262260437,"count":26,"distance":19.369998931884766,"speed":4.428787708282471},{"calorie":3.069999933242798,"count":89,"distance":67.61000061035156,"speed":4.97086763381958},{"calorie":0.0,"count":0,"distance":0.0,"speed":0.0},{"calorie":0.0,"count":0,"distance":0.0,"speed":0.0},{"calorie":2.9100000858306885,"count":75,"distance":55.93000030517578,"speed":4.570581436157227},{"calorie":0.0,"count":0,"distance":0.0,"speed":0.0},{"calorie":0.0,"count":0,"distance":0.0,"speed":0.0},{"calorie":0.0,"count":0,"distance":0.0,"speed":0.0},{"calorie":0.0,"count":0,"distance":0.0,"speed":0.0},{"calorie":0.0,"count":0,"distance":0.0,"speed":0.0},{"calorie":0.0,"count":0,"distance":0.0,"speed":0.0},{"calorie":0.0,"count":0,"distance":0.0,"speed":0.0},{"calorie":0.0,"count":0,"distance":0.0,"speed":0.0},{"calorie":0.0,"count":0,"distance":0.0,"speed":0.0},{"calorie":0.0,"count":0,"distance":0.0,"speed":0.0},{"calorie":0.0,"count":0,"distance":0.0,"speed":0.0},{"calorie":0.0,"count":0,"distance":0.0,"speed":0.0},{"calorie":0.0,"count":0,"distance":0.0,"speed":0.0},{"calorie":2.030000001192093,"count":53,"distance":39.079999923706055,"speed":4.313975811004639},{"calorie":0.0,"count":0,"distance":0.0,"speed":0.0},{"calorie":0.0,"count":0,"distance":0.0,"speed":0.0},{"calorie":0.0,"count":0,"distance":0.0,"speed":0.0},{"calorie":0.0,"count":0,"distance":0.0,"speed":0.0},{"calorie":0.0,"count":0,"distance":0.0,"speed":0.0},{"calorie":0.0,"count":0,"distance":0.0,"speed":0.0},{"calorie":0.0,"count":0,"distance":0.0,"speed":0.0},{"calorie":0.0,"count":0,"distance":0.0,"speed":0.0},{"calorie":0.0,"count":0,"distance":0.0,"speed":0.0},{"calorie":0.0,"count":0,"distance":0.0,"speed":0.0},{"calorie":0.0,"count":0,"distance":0.0,"speed":0.0},{"calorie":0.0,"count":0,"distance":0.0,"speed":0.0},{"calorie":0.0,"count":0,"distance":0.0,"speed":0.0},{"calorie":0.0,"count":0,"distance":0.0,"speed":0.0},{"calorie":0.0,"count":0,"distance":0.0,"speed":0.0},{"calorie":0.0,"count":0,"distance":0.0,"speed":0.0}]