[{"end_time":1740070919000,"flag":1,"level":1,"score":28,"score_max":28,"score_min":28,"start_time":1740070860000},{"end_time":1740070979000,"flag":1,"level":1,"score":74,"score_max":74,"score_min":28,"start_time":1740070920000},{"end_time":1740071399000,"flag":1,"level":1,"score":16,"score_max":74,"score_min":16,"start_time":1740071340000},{"end_time":1740071399000,"flag":1,"level":1,"score":1,"score_max":74,"score_min":1,"start_time":1740071340000},{"end_time":1740071459000,"flag":1,"level":1,"score":2,"score_max":74,"score_min":1,"start_time":1740071400000},{"end_time":1740071519000,"flag":1,"level":1,"score":69,"score_max":74,"score_min":1,"start_time":1740071460000},{"end_time":1740071519000,"flag":1,"level":1,"score":100,"score_max":100,"score_min":1,"start_time":1740071460000},{"end_time":1740071579000,"flag":1,"level":1,"score":0,"score_max":100,"score_min":0,"start_time":1740071520000},{"end_time":1740071579000,"flag":1,"level":1,"score":0,"score_max":100,"score_min":0,"start_time":1740071520000},{"end_time":1740072059000,"flag":1,"level":1,"score":6,"score_max":100,"score_min":0,"start_time":1740072000000},{"end_time":1740072119000,"flag":1,"level":1,"score":17,"score_max":100,"score_min":0,"start_time":1740072060000},{"end_time":1740072359000,"flag":1,"level":1,"score":41,"score_max":100,"score_min":0,"start_time":1740072300000},{"end_time":1740072539000,"flag":1,"level":1,"score":0,"score_max":100,"score_min":0,"start_time":1740072480000},{"end_time":1740072599000,"flag":1,"level":1,"score":0,"score_max":100,"score_min":0,"start_time":1740072540000},{"end_time":1740072719000,"flag":1,"level":1,"score":0,"score_max":100,"score_min":0,"start_time":1740072660000},{"end_time":1740072719000,"flag":1,"level":1,"score":0,"score_max":100,"score_min":0,"start_time":1740072660000},{"end_time":1740072779000,"flag":1,"level":1,"score":0,"score_max":100,"score_min":0,"start_time":1740072720000},{"end_time":1740072779000,"flag":1,"level":1,"score":0,"score_max":100,"score_min":0,"start_time":1740072720000},{"end_time":1740072839000,"flag":1,"level":1,"score":0,"score_max":100,"score_min":0,"start_time":1740072780000},{"end_time":1740072899000,"flag":1,"level":1,"score":0,"score_max":100,"score_min":0,"start_time":1740072840000},{"end_time":1740072899000,"flag":1,"level":1,"score":0,"score_max":100,"score_min":0,"start_time":1740072840000},{"end_time":1740072899000,"flag":1,"level":1,"score":0,"score_max":100,"score_min":0,"start_time":1740072840000}]