[{"mCalorie":0.0,"mDistance":0.0,"mNowHealthyStep":0,"mRunStepCount":0,"mSpeed":0.0,"mStartTime":0,"mStepCount":0,"mTimeUnit":600000,"mTotalActiveTime":0.0,"mWalkStepCount":0},{"mCalorie":0.0,"mDistance":0.0,"mNowHealthyStep":0,"mRunStepCount":0,"mSpeed":0.0,"mStartTime":0,"mStepCount":0,"mTimeUnit":600000,"mTotalActiveTime":0.0,"mWalkStepCount":0},{"mCalorie":0.0,"mDistance":0.0,"mNowHealthyStep":0,"mRunStepCount":0,"mSpeed":0.0,"mStartTime":0,"mStepCount":0,"mTimeUnit":600000,"mTotalActiveTime":0.0,"mWalkStepCount":0},{"mCalorie":0.0,"mDistance":0.0,"mNowHealthyStep":0,"mRunStepCount":0,"mSpeed":0.0,"mStartTime":0,"mStepCount":0,"mTimeUnit":600000,"mTotalActiveTime":0.0,"mWalkStepCount":0},{"mCalorie":0.0,"mDistance":0.0,"mNowHealthyStep":0,"mRunStepCount":0,"mSpeed":0.0,"mStartTime":0,"mStepCount":0,"mTimeUnit":600000,"mTotalActiveTime":0.0,"mWalkStepCount":0},{"mCalorie":0.0,"mDistance":0.0,"mNowHealthyStep":0,"mRunStepCount":0,"mSpeed":0.0,"mStartTime":0,"mStepCount":0,"mTimeUnit":600000,"mTotalActiveTime":0.0,"mWalkStepCount":0},{"mCalorie":0.0,"mDistance":0.0,"mNowHealthyStep":0,"mRunStepCount":0,"mSpeed":0.0,"mStartTime":0,"mStepCount":0,"mTimeUnit":600000,"mTotalActiveTime":0.0,"mWalkStepCount":0},{"mCalorie":0.0,"mDistance":0.0,"mNowHealthyStep":0,"mRunStepCount":0,"mSpeed":0.0,"mStartTime":0,"mStepCount":0,"mTimeUnit":600000,"mTotalActiveTime":0.0,"mWalkStepCount":0},{"mCalorie":0.0,"mDistance":0.0,"mNowHealthyStep":0,"mRunStepCount":0,"mSpeed":0.0,"mStartTime":0,"mStepCount":0,"mTimeUnit":600000,"mTotalActiveTime":0.0,"mWalkStepCount":0},{"mCalorie":0.0,"mDistance":0.0,"mNowHealthyStep":0,"mRunStepCount":0,"mSpeed":0.0,"mStartTime":0,"mStepCount":0,"mTimeUnit":600000,"mTotalActiveTime":0.0,"mWalkStepCount":0},{"mCalorie":0.0,"mDistance":0.0,"mNowHealthyStep":0,"mRunStepCount":0,"mSpeed":0.0,"mStartTime":0,"mStepCount":0,"mTimeUnit":600000,"mTotalActiveTime":0.0,"mWalkStepCount":0},{"mCalorie":0.0,"mDistance":0.0,"mNowHealthyStep":0,"mRunStepCount":0,"mSpeed":0.0,"mStartTime":0,"mStepCount":0,"mTimeUnit":600000,"mTotalActiveTime":0.0,"mWalkStepCount":0},{"mCalorie":0.0,"mDistance":0.0,"mNowHealthyStep":0,"mRunStepCount":0,"mSpeed":0.0,"mStartTime":0,"mStepCount":0,"mTimeUnit":600000,"mTotalActiveTime":0.0,"mWalkStepCount":0},{"mCalorie":0.0,"mDistance":0.0,"mNowHealthyStep":0,"mRunStepCount":0,"mSpeed":0.0,"mStartTime":0,"mStepCount":0,"mTimeUnit":600000,"mTotalActiveTime":0.0,"mWalkStepCount":0},{"mCalorie":0.0,"mDistance":0.0,"mNowHealthyStep":0,"mRunStepCount":0,"mSpeed":0.0,"mStartTime":0,"mStepCount":0,"mTimeUnit":600000,"mTotalActiveTime":0.0,"mWalkStepCount":0},{"mCalorie":0.0,"mDistance":0.0,"mNowHealthyStep":0,"mRunStepCount":0,"mSpeed":0.0,"mStartTime":0,"mStepCount":0,"mTimeUnit":600000,"mTotalActiveTime":0.0,"mWalkStepCount":0},{"mCalorie":0.0,"mDistance":0.0,"mNowHealthyStep":0,"mRunStepCount":0,"mSpeed":0.0,"mStartTime":0,"mStepCount":0,"mTimeUnit":600000,"mTotalActiveTime":0.0,"mWalkStepCount":0},{"mCalorie":0.0,"mDistance":0.0,"mNowHealthyStep":0,"mRunStepCount":0,"mSpeed":0.0,"mStartTime":0,"mStepCount":0,"mTimeUnit":600000,"mTotalActiveTime":0.0,"mWalkStepCount":0},{"mCalorie":0.0,"mDistance":0.0,"mNowHealthyStep":0,"mRunStepCount":0,"mSpeed":0.0,"mStartTime":0,"mStepCount":0,"mTimeUnit":600000,"mTotalActiveTime":0.0,"mWalkStepCount":0},{"mCalorie":0.0,"mDistance":0.0,"mNowHealthyStep":0,"mRunStepCount":0,"mSpeed":0.0,"mStartTime":0,"mStepCount":0,"mTimeUnit":600000,"mTotalActiveTime":0.0,"mWalkStepCount":0},{"mCalorie":0.0,"mDistance":0.0,"mNowHealthyStep":0,"mRunStepCount":0,"mSpeed":0.0,"mStartTime":0,"mStepCount":0,"mTimeUnit":600000,"mTotalActiveTime":0.0,"mWalkStepCount":0},{"mCalorie":0.0,"mDistance":0.0,"mNowHealthyStep":0,"mRunStepCount":0,"mSpeed":0.0,"mStartTime":0,"mStepCount":0,"mTimeUnit":600000,"mTotalActiveTime":0.0,"mWalkStepCount":0},{"mCalorie":0.0,"mDistance":0.0,"mNowHealthyStep":0,"mRunStepCount":0,"mSpeed":0.0,"mStartTime":0,"mStepCount":0,"mTimeUnit":600000,"mTotalActiveTime":0.0,"mWalkStepCount":0},{"mCalorie":0.0,"mDistance":0.0,"mNowHealthyStep":0,"mRunStepCount":0,"mSpeed":0.0,"mStartTime":0,"mStepCount":0,"mTimeUnit":600000,"mTotalActiveTime":0.0,"mWalkStepCount":0},{"mCalorie":0.0,"mDistance":0.0,"mNowHealthyStep":0,"mRunStepCount":0,"mSpeed":0.0,"mStartTime":0,"mStepCount":0,"mTimeUnit":600000,"mTotalActiveTime":0.0,"mWalkStepCount":0},{"mCalorie":0.0,"mDistance":0.0,"mNowHealthyStep":0,"mRunStepCount":0,"mSpeed":0.0,"mStartTime":0,"mStepCount":0,"mTimeUnit":600000,"mTotalActiveTime":0.0,"mWalkStepCount":0},{"mCalorie":0.0,"mDistance":0.0,"mNowHealthyStep":0,"mRunStepCount":0,"mSpeed":0.0,"mStartTime":0,"mStepCount":0,"mTimeUnit":600000,"mTotalActiveTime":0.0,"mWalkStepCount":0},{"mCalorie":0.0,"mDistance":0.0,"mNowHealthyStep":0,"mRunStepCount":0,"mSpeed":0.0,"mStartTime":0,"mStepCount":0,"mTimeUnit":600000,"mTotalActiveTime":0.0,"mWalkStepCount":0},{"mCalorie":0.0,"mDistance":0.0,"mNowHealthyStep":0,"mRunStepCount":0,"mSpeed":0.0,"mStartTime":0,"mStepCount":0,"mTimeUnit":600000,"mTotalActiveTime":0.0,"mWalkStepCount":0},{"mCalorie":0.0,"mDistance":0.0,"mNowHealthyStep":0,"mRunStepCount":0,"mSpeed":0.0,"mStartTime":0,"mStepCount":0,"mTimeUnit":600000,"mTotalActiveTime":0.0,"mWalkStepCount":0},{"mCalorie":0.0,"mDistance":0.0,"mNowHealthyStep":0,"mRunStepCount":0,"mSpeed":0.0,"mStartTime":0,"mStepCount":0,"mTimeUnit":600000,"mTotalActiveTime":0.0,"mWalkStepCount":0},{"mCalorie":0.0,"mDistance":0.0,"mNowHealthyStep":0,"mRunStepCount":0,"mSpeed":0.0,"mStartTime":0,"mStepCount":0,"mTimeUnit":600000,"mTotalActiveTime":0.0,"mWalkStepCount":0},{"mCalorie":1.2699999809265137,"mDistance":25.399999618530273,"mNowHealthyStep":0,"mRunStepCount":0,"mSpeed":4.420017719268799,"mStartTime":0,"mStepCount":34,"mTimeUnit":600000,"mTotalActiveTime":20687.699420581896,"mWalkStepCount":34},{"mCalorie":2.319999933242798,"mDistance":46.09999942779541,"mNowHealthyStep":0,"mRunStepCount":0,"mSpeed":4.404778003692627,"mStartTime":0,"mStepCount":62,"mTimeUnit":600000,"mTotalActiveTime":37677.269219740985,"mWalkStepCount":62},{"mCalorie":5.6700000166893005,"mDistance":111.52000045776367,"mNowHealthyStep":0,"mRunStepCount":0,"mSpeed":4.186600208282471,"mStartTime":0,"mStepCount":151,"mTimeUnit":600000,"mTotalActiveTime":95894.51219954323,"mWalkStepCount":151},{"mCalorie":1.6399999856948853,"mDistance":31.369999885559082,"mNowHealthyStep":0,"mRunStepCount":0,"mSpeed":3.96772837638855,"mStartTime":0,"mStepCount":43,"mTimeUnit":600000,"mTotalActiveTime":28462.633015413212,"mWalkStepCount":43},{"mCalorie":0.0,"mDistance":0.0,"mNowHealthyStep":0,"mRunStepCount":0,"mSpeed":0.0,"mStartTime":0,"mStepCount":0,"mTimeUnit":600000,"mTotalActiveTime":0.0,"mWalkStepCount":0},{"mCalorie":0.0,"mDistance":0.0,"mNowHealthyStep":0,"mRunStepCount":0,"mSpeed":0.0,"mStartTime":0,"mStepCount":0,"mTimeUnit":600000,"mTotalActiveTime":0.0,"mWalkStepCount":0},{"mCalorie":0.5299999713897705,"mDistance":11.420000076293945,"mNowHealthyStep":0,"mRunStepCount":0,"mSpeed":4.700000286102295,"mStartTime":0,"mStepCount":15,"mTimeUnit":600000,"mTotalActiveTime":8747.233568522257,"mWalkStepCount":15},{"mCalorie":0.0,"mDistance":0.0,"mNowHealthyStep":0,"mRunStepCount":0,"mSpeed":0.0,"mStartTime":0,"mStepCount":0,"mTimeUnit":600000,"mTotalActiveTime":0.0,"mWalkStepCount":0},{"mCalorie":0.0,"mDistance":0.0,"mNowHealthyStep":0,"mRunStepCount":0,"mSpeed":0.0,"mStartTime":0,"mStepCount":0,"mTimeUnit":600000,"mTotalActiveTime":0.0,"mWalkStepCount":0},{"mCalorie":1.9700000286102295,"mDistance":40.43000030517578,"mNowHealthyStep":0,"mRunStepCount":0,"mSpeed":4.600000381469727,"mStartTime":0,"mStepCount":53,"mTimeUnit":600000,"mTotalActiveTime":31640.867180130404,"mWalkStepCount":53},{"mCalorie":7.640000104904175,"mDistance":145.69000053405762,"mNowHealthyStep":0,"mRunStepCount":0,"mSpeed":4.3797607421875,"mStartTime":0,"mStepCount":197,"mTimeUnit":600000,"mTotalActiveTime":119751.74956523342,"mWalkStepCount":197},{"mCalorie":26.84999966621399,"mDistance":505.15999603271484,"mNowHealthyStep":0,"mRunStepCount":0,"mSpeed":4.589866638183594,"mStartTime":0,"mStepCount":675,"mTimeUnit":600000,"mTotalActiveTime":396215.4412175107,"mWalkStepCount":675},{"mCalorie":5.890000015497208,"mDistance":112.50000095367432,"mNowHealthyStep":0,"mRunStepCount":0,"mSpeed":4.475703239440918,"mStartTime":0,"mStepCount":151,"mTimeUnit":600000,"mTotalActiveTime":90488.57253522292,"mWalkStepCount":151},{"mCalorie":16.289999842643738,"mDistance":306.03999519348145,"mNowHealthyStep":0,"mRunStepCount":0,"mSpeed":4.209887981414795,"mStartTime":0,"mStepCount":415,"mTimeUnit":600000,"mTotalActiveTime":261703.88603043868,"mWalkStepCount":415},{"mCalorie":8.869999885559082,"mDistance":169.12000274658203,"mNowHealthyStep":0,"mRunStepCount":0,"mSpeed":4.294485569000244,"mStartTime":0,"mStepCount":229,"mTimeUnit":600000,"mTotalActiveTime":141770.65178930984,"mWalkStepCount":229},{"mCalorie":2.75,"mDistance":51.83999967575073,"mNowHealthyStep":0,"mRunStepCount":0,"mSpeed":3.9655725955963135,"mStartTime":0,"mStepCount":71,"mTimeUnit":600000,"mTotalActiveTime":47061.04700867272,"mWalkStepCount":71},{"mCalorie":11.299999751150608,"mDistance":213.9200041294098,"mNowHealthyStep":0,"mRunStepCount":0,"mSpeed":4.680174827575684,"mStartTime":0,"mStepCount":286,"mTimeUnit":600000,"mTotalActiveTime":164547.70840399657,"mWalkStepCount":286},{"mCalorie":1.900000050663948,"mDistance":36.57000017166138,"mNowHealthyStep":0,"mRunStepCount":0,"mSpeed":4.364902019500732,"mStartTime":0,"mStepCount":49,"mTimeUnit":600000,"mTotalActiveTime":30161.502735392794,"mWalkStepCount":49},{"mCalorie":2.1700000017881393,"mDistance":41.22000312805176,"mNowHealthyStep":0,"mRunStepCount":0,"mSpeed":4.077385425567627,"mStartTime":0,"mStepCount":56,"mTimeUnit":600000,"mTotalActiveTime":36393.91263893718,"mWalkStepCount":56},{"mCalorie":0.0,"mDistance":0.0,"mNowHealthyStep":0,"mRunStepCount":0,"mSpeed":0.0,"mStartTime":0,"mStepCount":0,"mTimeUnit":600000,"mTotalActiveTime":0.0,"mWalkStepCount":0},{"mCalorie":0.3400000035762787,"mDistance":6.360000133514404,"mNowHealthyStep":0,"mRunStepCount":0,"mSpeed":3.2662971019744873,"mStartTime":0,"mStepCount":9,"mTimeUnit":600000,"mTotalActiveTime":7009.772768928812,"mWalkStepCount":9},{"mCalorie":4.440000057220459,"mDistance":87.77999687194824,"mNowHealthyStep":0,"mRunStepCount":0,"mSpeed":4.50264835357666,"mStartTime":0,"mStepCount":117,"mTimeUnit":600000,"mTotalActiveTime":70182.69532440582,"mWalkStepCount":117},{"mCalorie":0.0,"mDistance":0.0,"mNowHealthyStep":0,"mRunStepCount":0,"mSpeed":0.0,"mStartTime":0,"mStepCount":0,"mTimeUnit":600000,"mTotalActiveTime":0.0,"mWalkStepCount":0},{"mCalorie":0.0,"mDistance":0.0,"mNowHealthyStep":0,"mRunStepCount":0,"mSpeed":0.0,"mStartTime":0,"mStepCount":0,"mTimeUnit":600000,"mTotalActiveTime":0.0,"mWalkStepCount":0},{"mCalorie":0.0,"mDistance":0.0,"mNowHealthyStep":0,"mRunStepCount":0,"mSpeed":0.0,"mStartTime":0,"mStepCount":0,"mTimeUnit":600000,"mTotalActiveTime":0.0,"mWalkStepCount":0},{"mCalorie":0.0,"mDistance":0.0,"mNowHealthyStep":0,"mRunStepCount":0,"mSpeed":0.0,"mStartTime":0,"mStepCount":0,"mTimeUnit":600000,"mTotalActiveTime":0.0,"mWalkStepCount":0},{"mCalorie":0.0,"mDistance":0.0,"mNowHealthyStep":0,"mRunStepCount":0,"mSpeed":0.0,"mStartTime":0,"mStepCount":0,"mTimeUnit":600000,"mTotalActiveTime":0.0,"mWalkStepCount":0},{"mCalorie":0.0,"mDistance":0.0,"mNowHealthyStep":0,"mRunStepCount":0,"mSpeed":0.0,"mStartTime":0,"mStepCount":0,"mTimeUnit":600000,"mTotalActiveTime":0.0,"mWalkStepCount":0},{"mCalorie":0.0,"mDistance":0.0,"mNowHealthyStep":0,"mRunStepCount":0,"mSpeed":0.0,"mStartTime":0,"mStepCount":0,"mTimeUnit":600000,"mTotalActiveTime":0.0,"mWalkStepCount":0},{"mCalorie":0.0,"mDistance":0.0,"mNowHealthyStep":0,"mRunStepCount":0,"mSpeed":0.0,"mStartTime":0,"mStepCount":0,"mTimeUnit":600000,"mTotalActiveTime":0.0,"mWalkStepCount":0},{"mCalorie":0.0,"mDistance":0.0,"mNowHealthyStep":0,"mRunStepCount":0,"mSpeed":0.0,"mStartTime":0,"mStepCount":0,"mTimeUnit":600000,"mTotalActiveTime":0.0,"mWalkStepCount":0},{"mCalorie":0.0,"mDistance":0.0,"mNowHealthyStep":0,"mRunStepCount":0,"mSpeed":0.0,"mStartTime":0,"mStepCount":0,"mTimeUnit":600000,"mTotalActiveTime":0.0,"mWalkStepCount":0},{"mCalorie":0.0,"mDistance":0.0,"mNowHealthyStep":0,"mRunStepCount":0,"mSpeed":0.0,"mStartTime":0,"mStepCount":0,"mTimeUnit":600000,"mTotalActiveTime":0.0,"mWalkStepCount":0},{"mCalorie":0.0,"mDistance":0.0,"mNowHealthyStep":0,"mRunStepCount":0,"mSpeed":0.0,"mStartTime":0,"mStepCount":0,"mTimeUnit":600000,"mTotalActiveTime":0.0,"mWalkStepCount":0},{"mCalorie":0.0,"mDistance":0.0,"mNowHealthyStep":0,"mRunStepCount":0,"mSpeed":0.0,"mStartTime":0,"mStepCount":0,"mTimeUnit":600000,"mTotalActiveTime":0.0,"mWalkStepCount":0},{"mCalorie":0.0,"mDistance":0.0,"mNowHealthyStep":0,"mRunStepCount":0,"mSpeed":0.0,"mStartTime":0,"mStepCount":0,"mTimeUnit":600000,"mTotalActiveTime":0.0,"mWalkStepCount":0},{"mCalorie":0.0,"mDistance":0.0,"mNowHealthyStep":0,"mRunStepCount":0,"mSpeed":0.0,"mStartTime":0,"mStepCount":0,"mTimeUnit":600000,"mTotalActiveTime":0.0,"mWalkStepCount":0},{"mCalorie":0.0,"mDistance":0.0,"mNowHealthyStep":0,"mRunStepCount":0,"mSpeed":0.0,"mStartTime":0,"mStepCount":0,"mTimeUnit":600000,"mTotalActiveTime":0.0,"mWalkStepCount":0},{"mCalorie":0.0,"mDistance":0.0,"mNowHealthyStep":0,"mRunStepCount":0,"mSpeed":0.0,"mStartTime":0,"mStepCount":0,"mTimeUnit":600000,"mTotalActiveTime":0.0,"mWalkStepCount":0},{"mCalorie":0.0,"mDistance":0.0,"mNowHealthyStep":0,"mRunStepCount":0,"mSpeed":0.0,"mStartTime":0,"mStepCount":0,"mTimeUnit":600000,"mTotalActiveTime":0.0,"mWalkStepCount":0},{"mCalorie":0.0,"mDistance":0.0,"mNowHealthyStep":0,"mRunStepCount":0,"mSpeed":0.0,"mStartTime":0,"mStepCount":0,"mTimeUnit":600000,"mTotalActiveTime":0.0,"mWalkStepCount":0},{"mCalorie":2.409999966621399,"mDistance":58.58999824523926,"mNowHealthyStep":0,"mRunStepCount":0,"mSpeed":4.424807071685791,"mStartTime":0,"mStepCount":79,"mTimeUnit":600000,"mTotalActiveTime":47668.51856801456,"mWalkStepCount":79},{"mCalorie":14.899999678134918,"mDistance":366.58999252319336,"mNowHealthyStep":0,"mRunStepCount":0,"mSpeed":4.571748733520508,"mStartTime":0,"mStepCount":491,"mTimeUnit":600000,"mTotalActiveTime":288669.40325254726,"mWalkStepCount":491},{"mCalorie":22.35999858379364,"mDistance":550.5599880218506,"mNowHealthyStep":0,"mRunStepCount":0,"mSpeed":4.50738000869751,"mStartTime":0,"mStepCount":738,"mTimeUnit":600000,"mTotalActiveTime":439726.82673729945,"mWalkStepCount":738},{"mCalorie":0.0,"mDistance":0.0,"mNowHealthyStep":0,"mRunStepCount":0,"mSpeed":0.0,"mStartTime":0,"mStepCount":0,"mTimeUnit":600000,"mTotalActiveTime":0.0,"mWalkStepCount":0},{"mCalorie":3.0199999809265137,"mDistance":71.71000003814697,"mNowHealthyStep":0,"mRunStepCount":0,"mSpeed":4.208640098571777,"mStartTime":0,"mStepCount":98,"mTimeUnit":600000,"mTotalActiveTime":61339.529418776445,"mWalkStepCount":98},{"mCalorie":5.7800000458955765,"mDistance":137.11000204086304,"mNowHealthyStep":0,"mRunStepCount":0,"mSpeed":4.433487415313721,"mStartTime":0,"mStepCount":184,"mTimeUnit":600000,"mTotalActiveTime":111333.5727127939,"mWalkStepCount":184},{"mCalorie":0.23999999463558197,"mDistance":4.96999979019165,"mNowHealthyStep":0,"mRunStepCount":0,"mSpeed":3.3000001907348633,"mStartTime":0,"mStepCount":7,"mTimeUnit":600000,"mTotalActiveTime":5421.817639563726,"mWalkStepCount":7},{"mCalorie":4.180000051856041,"mDistance":96.66999912261963,"mNowHealthyStep":0,"mRunStepCount":0,"mSpeed":4.4106125831604,"mStartTime":0,"mStepCount":131,"mTimeUnit":600000,"mTotalActiveTime":78903.32797905986,"mWalkStepCount":131},{"mCalorie":17.579999446868896,"mDistance":432.15999031066895,"mNowHealthyStep":0,"mRunStepCount":0,"mSpeed":4.565069675445557,"mStartTime":0,"mStepCount":581,"mTimeUnit":600000,"mTotalActiveTime":340800.0571348299,"mWalkStepCount":581},{"mCalorie":12.899994015693665,"mDistance":319.02000427246094,"mNowHealthyStep":0,"mRunStepCount":0,"mSpeed":4.619869232177734,"mStartTime":0,"mStepCount":426,"mTimeUnit":600000,"mTotalActiveTime":248594.05968735542,"mWalkStepCount":426},{"mCalorie":0.0,"mDistance":0.0,"mNowHealthyStep":0,"mRunStepCount":0,"mSpeed":0.0,"mStartTime":0,"mStepCount":0,"mTimeUnit":600000,"mTotalActiveTime":0.0,"mWalkStepCount":0},{"mCalorie":0.0,"mDistance":0.0,"mNowHealthyStep":0,"mRunStepCount":0,"mSpeed":0.0,"mStartTime":0,"mStepCount":0,"mTimeUnit":600000,"mTotalActiveTime":0.0,"mWalkStepCount":0},{"mCalorie":0.0,"mDistance":0.0,"mNowHealthyStep":0,"mRunStepCount":0,"mSpeed":0.0,"mStartTime":0,"mStepCount":0,"mTimeUnit":600000,"mTotalActiveTime":0.0,"mWalkStepCount":0},{"mCalorie":0.33000001311302185,"mDistance":7.059999942779541,"mNowHealthyStep":0,"mRunStepCount":0,"mSpeed":3.499999761581421,"mStartTime":0,"mStepCount":10,"mTimeUnit":600000,"mTotalActiveTime":7261.714721524015,"mWalkStepCount":10},{"mCalorie":25.77999985218048,"mDistance":632.319995880127,"mNowHealthyStep":0,"mRunStepCount":0,"mSpeed":4.30108642578125,"mStartTime":0,"mStepCount":856,"mTimeUnit":600000,"mTotalActiveTime":529250.4823913529,"mWalkStepCount":856},{"mCalorie":20.860000133514404,"mDistance":513.1099967956543,"mNowHealthyStep":0,"mRunStepCount":0,"mSpeed":4.448758602142334,"mStartTime":0,"mStepCount":691,"mTimeUnit":600000,"mTotalActiveTime":415216.0354017918,"mWalkStepCount":691},{"mCalorie":5.549999952316284,"mDistance":126.74000358581543,"mNowHealthyStep":0,"mRunStepCount":0,"mSpeed":4.04030704498291,"mStartTime":0,"mStepCount":174,"mTimeUnit":600000,"mTotalActiveTime":112928.0517650132,"mWalkStepCount":174},{"mCalorie":5.119999974966049,"mDistance":119.89999914169312,"mNowHealthyStep":0,"mRunStepCount":0,"mSpeed":4.032703876495361,"mStartTime":0,"mStepCount":164,"mTimeUnit":600000,"mTotalActiveTime":107034.89024788933,"mWalkStepCount":164},{"mCalorie":29.519999861717224,"mDistance":736.2899971008301,"mNowHealthyStep":0,"mRunStepCount":0,"mSpeed":4.6439433097839355,"mStartTime":0,"mStepCount":984,"mTimeUnit":600000,"mTotalActiveTime":570774.3949042361,"mWalkStepCount":984},{"mCalorie":26.13999977707863,"mDistance":650.0700078010559,"mNowHealthyStep":0,"mRunStepCount":0,"mSpeed":4.608026027679443,"mStartTime":0,"mStepCount":870,"mTimeUnit":600000,"mTotalActiveTime":507864.307697247,"mWalkStepCount":870},{"mCalorie":1.2099999785423279,"mDistance":27.130000114440918,"mNowHealthyStep":0,"mRunStepCount":0,"mSpeed":4.265439987182617,"mStartTime":0,"mStepCount":37,"mTimeUnit":600000,"mTotalActiveTime":22897.519718005395,"mWalkStepCount":37},{"mCalorie":12.689999997615814,"mDistance":304.66999435424805,"mNowHealthyStep":0,"mRunStepCount":0,"mSpeed":4.40919303894043,"mStartTime":0,"mStepCount":410,"mTimeUnit":600000,"mTotalActiveTime":248755.70901805663,"mWalkStepCount":410},{"mCalorie":0.0,"mDistance":0.0,"mNowHealthyStep":0,"mRunStepCount":0,"mSpeed":0.0,"mStartTime":0,"mStepCount":0,"mTimeUnit":600000,"mTotalActiveTime":0.0,"mWalkStepCount":0},{"mCalorie":2.4800000190734863,"mDistance":57.99000072479248,"mNowHealthyStep":0,"mRunStepCount":0,"mSpeed":3.9000003337860107,"mStartTime":0,"mStepCount":80,"mTimeUnit":600000,"mTotalActiveTime":53529.22685690918,"mWalkStepCount":80},{"mCalorie":2.0,"mDistance":46.16000032424927,"mNowHealthyStep":0,"mRunStepCount":0,"mSpeed":4.03763484954834,"mStartTime":0,"mStepCount":63,"mTimeUnit":600000,"mTotalActiveTime":41156.7673505121,"mWalkStepCount":63},{"mCalorie":0.0,"mDistance":0.0,"mNowHealthyStep":0,"mRunStepCount":0,"mSpeed":0.0,"mStartTime":0,"mStepCount":0,"mTimeUnit":600000,"mTotalActiveTime":0.0,"mWalkStepCount":0},{"mCalorie":0.0,"mDistance":0.0,"mNowHealthyStep":0,"mRunStepCount":0,"mSpeed":0.0,"mStartTime":0,"mStepCount":0,"mTimeUnit":600000,"mTotalActiveTime":0.0,"mWalkStepCount":0},{"mCalorie":0.0,"mDistance":0.0,"mNowHealthyStep":0,"mRunStepCount":0,"mSpeed":0.0,"mStartTime":0,"mStepCount":0,"mTimeUnit":600000,"mTotalActiveTime":0.0,"mWalkStepCount":0},{"mCalorie":3.060000089928508,"mDistance":73.91999840736389,"mNowHealthyStep":0,"mRunStepCount":0,"mSpeed":4.632652759552002,"mStartTime":0,"mStepCount":99,"mTimeUnit":600000,"mTotalActiveTime":57442.6820903192,"mWalkStepCount":99},{"mCalorie":5.990000009536743,"mDistance":142.88999462127686,"mNowHealthyStep":0,"mRunStepCount":0,"mSpeed":4.6428375244140625,"mStartTime":0,"mStepCount":190,"mTimeUnit":600000,"mTotalActiveTime":110795.17051829824,"mWalkStepCount":190},{"mCalorie":2.94999997317791,"mDistance":68.81999826431274,"mNowHealthyStep":0,"mRunStepCount":0,"mSpeed":4.788012981414795,"mStartTime":0,"mStepCount":89,"mTimeUnit":600000,"mTotalActiveTime":51744.22136081186,"mWalkStepCount":89},{"mCalorie":13.249999850988388,"mDistance":323.159996509552,"mNowHealthyStep":0,"mRunStepCount":0,"mSpeed":4.422799587249756,"mStartTime":0,"mStepCount":434,"mTimeUnit":600000,"mTotalActiveTime":263040.6338275028,"mWalkStepCount":434},{"mCalorie":0.0,"mDistance":0.0,"mNowHealthyStep":0,"mRunStepCount":0,"mSpeed":0.0,"mStartTime":0,"mStepCount":0,"mTimeUnit":600000,"mTotalActiveTime":0.0,"mWalkStepCount":0},{"mCalorie":0.2199999988079071,"mDistance":5.590000152587891,"mNowHealthyStep":0,"mRunStepCount":0,"mSpeed":5.999999523162842,"mStartTime":0,"mStepCount":7,"mTimeUnit":600000,"mTotalActiveTime":3354.0003581047345,"mWalkStepCount":7},{"mCalorie":0.25999999046325684,"mDistance":5.75,"mNowHealthyStep":0,"mRunStepCount":0,"mSpeed":3.536062240600586,"mStartTime":0,"mStepCount":8,"mTimeUnit":600000,"mTotalActiveTime":5853.969356739657,"mWalkStepCount":8},{"mCalorie":0.0,"mDistance":0.0,"mNowHealthyStep":0,"mRunStepCount":0,"mSpeed":0.0,"mStartTime":0,"mStepCount":0,"mTimeUnit":600000,"mTotalActiveTime":0.0,"mWalkStepCount":0},{"mCalorie":0.41999998688697815,"mDistance":9.609999656677246,"mNowHealthyStep":0,"mRunStepCount":0,"mSpeed":3.9000003337860107,"mStartTime":0,"mStepCount":13,"mTimeUnit":600000,"mTotalActiveTime":8870.768154640966,"mWalkStepCount":13},{"mCalorie":23.23999908566475,"mDistance":573.590009689331,"mNowHealthyStep":0,"mRunStepCount":0,"mSpeed":4.72178840637207,"mStartTime":0,"mStepCount":767,"mTimeUnit":600000,"mTotalActiveTime":437318.2037948986,"mWalkStepCount":767},{"mCalorie":30.519999265670776,"mDistance":759.619987487793,"mNowHealthyStep":0,"mRunStepCount":0,"mSpeed":4.69658088684082,"mStartTime":0,"mStepCount":1015,"mTimeUnit":600000,"mTotalActiveTime":582260.190677613,"mWalkStepCount":1015},{"mCalorie":12.39000004529953,"mDistance":307.15999698638916,"mNowHealthyStep":0,"mRunStepCount":0,"mSpeed":4.549773216247559,"mStartTime":0,"mStepCount":412,"mTimeUnit":600000,"mTotalActiveTime":243039.8127688023,"mWalkStepCount":412},{"mCalorie":0.0,"mDistance":0.0,"mNowHealthyStep":0,"mRunStepCount":0,"mSpeed":0.0,"mStartTime":0,"mStepCount":0,"mTimeUnit":600000,"mTotalActiveTime":0.0,"mWalkStepCount":0},{"mCalorie":0.0,"mDistance":0.0,"mNowHealthyStep":0,"mRunStepCount":0,"mSpeed":0.0,"mStartTime":0,"mStepCount":0,"mTimeUnit":600000,"mTotalActiveTime":0.0,"mWalkStepCount":0},{"mCalorie":0.0,"mDistance":0.0,"mNowHealthyStep":0,"mRunStepCount":0,"mSpeed":0.0,"mStartTime":0,"mStepCount":0,"mTimeUnit":600000,"mTotalActiveTime":0.0,"mWalkStepCount":0},{"mCalorie":0.0,"mDistance":0.0,"mNowHealthyStep":0,"mRunStepCount":0,"mSpeed":0.0,"mStartTime":0,"mStepCount":0,"mTimeUnit":600000,"mTotalActiveTime":0.0,"mWalkStepCount":0},{"mCalorie":0.0,"mDistance":0.0,"mNowHealthyStep":0,"mRunStepCount":0,"mSpeed":0.0,"mStartTime":0,"mStepCount":0,"mTimeUnit":600000,"mTotalActiveTime":0.0,"mWalkStepCount":0},{"mCalorie":0.0,"mDistance":0.0,"mNowHealthyStep":0,"mRunStepCount":0,"mSpeed":0.0,"mStartTime":0,"mStepCount":0,"mTimeUnit":600000,"mTotalActiveTime":0.0,"mWalkStepCount":0},{"mCalorie":9.46999979019165,"mDistance":232.6699981689453,"mNowHealthyStep":0,"mRunStepCount":0,"mSpeed":4.65339994430542,"mStartTime":0,"mStepCount":314,"mTimeUnit":600000,"mTotalActiveTime":180000.00693519652,"mWalkStepCount":314},{"mCalorie":29.84999990463257,"mDistance":739.3999900817871,"mNowHealthyStep":0,"mRunStepCount":0,"mSpeed":4.5811944007873535,"mStartTime":0,"mStepCount":995,"mTimeUnit":600000,"mTotalActiveTime":581036.2688804244,"mWalkStepCount":995},{"mCalorie":23.860000044107437,"mDistance":591.2399940490723,"mNowHealthyStep":0,"mRunStepCount":0,"mSpeed":4.483188152313232,"mStartTime":0,"mStepCount":794,"mTimeUnit":600000,"mTotalActiveTime":474765.68055435375,"mWalkStepCount":794},{"mCalorie":0.4699999988079071,"mDistance":10.850000381469727,"mNowHealthyStep":0,"mRunStepCount":0,"mSpeed":3.4000000953674316,"mStartTime":0,"mStepCount":15,"mTimeUnit":600000,"mTotalActiveTime":11488.235375790446,"mWalkStepCount":15},{"mCalorie":0.0,"mDistance":0.0,"mNowHealthyStep":0,"mRunStepCount":0,"mSpeed":0.0,"mStartTime":0,"mStepCount":0,"mTimeUnit":600000,"mTotalActiveTime":0.0,"mWalkStepCount":0},{"mCalorie":0.25999999046325684,"mDistance":5.96999979019165,"mNowHealthyStep":0,"mRunStepCount":0,"mSpeed":4.436619281768799,"mStartTime":0,"mStepCount":8,"mTimeUnit":600000,"mTotalActiveTime":4844.228877831833,"mWalkStepCount":8},{"mCalorie":0.0,"mDistance":0.0,"mNowHealthyStep":0,"mRunStepCount":0,"mSpeed":0.0,"mStartTime":0,"mStepCount":0,"mTimeUnit":600000,"mTotalActiveTime":0.0,"mWalkStepCount":0},{"mCalorie":0.0,"mDistance":0.0,"mNowHealthyStep":0,"mRunStepCount":0,"mSpeed":0.0,"mStartTime":0,"mStepCount":0,"mTimeUnit":600000,"mTotalActiveTime":0.0,"mWalkStepCount":0},{"mCalorie":0.0,"mDistance":0.0,"mNowHealthyStep":0,"mRunStepCount":0,"mSpeed":0.0,"mStartTime":0,"mStepCount":0,"mTimeUnit":600000,"mTotalActiveTime":0.0,"mWalkStepCount":0},{"mCalorie":0.0,"mDistance":0.0,"mNowHealthyStep":0,"mRunStepCount":0,"mSpeed":0.0,"mStartTime":0,"mStepCount":0,"mTimeUnit":600000,"mTotalActiveTime":0.0,"mWalkStepCount":0},{"mCalorie":0.0,"mDistance":0.0,"mNowHealthyStep":0,"mRunStepCount":0,"mSpeed":0.0,"mStartTime":0,"mStepCount":0,"mTimeUnit":600000,"mTotalActiveTime":0.0,"mWalkStepCount":0},{"mCalorie":0.0,"mDistance":0.0,"mNowHealthyStep":0,"mRunStepCount":0,"mSpeed":0.0,"mStartTime":0,"mStepCount":0,"mTimeUnit":600000,"mTotalActiveTime":0.0,"mWalkStepCount":0},{"mCalorie":0.0,"mDistance":0.0,"mNowHealthyStep":0,"mRunStepCount":0,"mSpeed":0.0,"mStartTime":0,"mStepCount":0,"mTimeUnit":600000,"mTotalActiveTime":0.0,"mWalkStepCount":0},{"mCalorie":0.0,"mDistance":0.0,"mNowHealthyStep":0,"mRunStepCount":0,"mSpeed":0.0,"mStartTime":0,"mStepCount":0,"mTimeUnit":600000,"mTotalActiveTime":0.0,"mWalkStepCount":0},{"mCalorie":0.0,"mDistance":0.0,"mNowHealthyStep":0,"mRunStepCount":0,"mSpeed":0.0,"mStartTime":0,"mStepCount":0,"mTimeUnit":600000,"mTotalActiveTime":0.0,"mWalkStepCount":0},{"mCalorie":0.0,"mDistance":0.0,"mNowHealthyStep":0,"mRunStepCount":0,"mSpeed":0.0,"mStartTime":0,"mStepCount":0,"mTimeUnit":600000,"mTotalActiveTime":0.0,"mWalkStepCount":0},{"mCalorie":0.0,"mDistance":0.0,"mNowHealthyStep":0,"mRunStepCount":0,"mSpeed":0.0,"mStartTime":0,"mStepCount":0,"mTimeUnit":600000,"mTotalActiveTime":0.0,"mWalkStepCount":0},{"mCalorie":0.0,"mDistance":0.0,"mNowHealthyStep":0,"mRunStepCount":0,"mSpeed":0.0,"mStartTime":0,"mStepCount":0,"mTimeUnit":600000,"mTotalActiveTime":0.0,"mWalkStepCount":0},{"mCalorie":0.0,"mDistance":0.0,"mNowHealthyStep":0,"mRunStepCount":0,"mSpeed":0.0,"mStartTime":0,"mStepCount":0,"mTimeUnit":600000,"mTotalActiveTime":0.0,"mWalkStepCount":0},{"mCalorie":0.0,"mDistance":0.0,"mNowHealthyStep":0,"mRunStepCount":0,"mSpeed":0.0,"mStartTime":0,"mStepCount":0,"mTimeUnit":600000,"mTotalActiveTime":0.0,"mWalkStepCount":0},{"mCalorie":0.0,"mDistance":0.0,"mNowHealthyStep":0,"mRunStepCount":0,"mSpeed":0.0,"mStartTime":0,"mStepCount":0,"mTimeUnit":600000,"mTotalActiveTime":0.0,"mWalkStepCount":0},{"mCalorie":0.0,"mDistance":0.0,"mNowHealthyStep":0,"mRunStepCount":0,"mSpeed":0.0,"mStartTime":0,"mStepCount":0,"mTimeUnit":600000,"mTotalActiveTime":0.0,"mWalkStepCount":0},{"mCalorie":0.0,"mDistance":0.0,"mNowHealthyStep":0,"mRunStepCount":0,"mSpeed":0.0,"mStartTime":0,"mStepCount":0,"mTimeUnit":600000,"mTotalActiveTime":0.0,"mWalkStepCount":0},{"mCalorie":0.0,"mDistance":0.0,"mNowHealthyStep":0,"mRunStepCount":0,"mSpeed":0.0,"mStartTime":0,"mStepCount":0,"mTimeUnit":600000,"mTotalActiveTime":0.0,"mWalkStepCount":0},{"mCalorie":0.0,"mDistance":0.0,"mNowHealthyStep":0,"mRunStepCount":0,"mSpeed":0.0,"mStartTime":0,"mStepCount":0,"mTimeUnit":600000,"mTotalActiveTime":0.0,"mWalkStepCount":0}]