[{"end_time":1740020459000,"heart_rate":63,"heart_rate_max":66,"heart_rate_min":63,"start_time":1740020400000},{"end_time":1740020519000,"heart_rate":63,"heart_rate_max":66,"heart_rate_min":63,"start_time":1740020460000},{"end_time":1740020579000,"heart_rate":63,"heart_rate_max":66,"heart_rate_min":63,"start_time":1740020520000},{"end_time":1740020639000,"heart_rate":64,"heart_rate_max":66,"heart_rate_min":64,"start_time":1740020580000},{"end_time":1740020699000,"heart_rate":64,"heart_rate_max":66,"heart_rate_min":64,"start_time":1740020640000},{"end_time":1740020759000,"heart_rate":64,"heart_rate_max":67,"heart_rate_min":64,"start_time":1740020700000},{"end_time":1740020819000,"heart_rate":64,"heart_rate_max":66,"heart_rate_min":64,"start_time":1740020760000},{"end_time":1740020879000,"heart_rate":65,"heart_rate_max":66,"heart_rate_min":65,"start_time":1740020820000},{"end_time":1740020879000,"heart_rate":64,"heart_rate_max":66,"heart_rate_min":64,"start_time":1740020820000},{"end_time":1740020939000,"heart_rate":65,"heart_rate_max":97,"heart_rate_min":65,"start_time":1740020880000},{"end_time":1740020999000,"heart_rate":61,"heart_rate_max":84,"heart_rate_min":61,"start_time":1740020940000},{"end_time":1740021059000,"heart_rate":60,"heart_rate_max":62,"heart_rate_min":60,"start_time":1740021000000},{"end_time":1740021119000,"heart_rate":60,"heart_rate_max":62,"heart_rate_min":60,"start_time":1740021060000},{"end_time":1740021179000,"heart_rate":61,"heart_rate_max":64,"heart_rate_min":61,"start_time":1740021120000},{"end_time":1740021239000,"heart_rate":61,"heart_rate_max":63,"heart_rate_min":61,"start_time":1740021180000},{"end_time":1740021299000,"heart_rate":61,"heart_rate_max":68,"heart_rate_min":61,"start_time":1740021240000},{"end_time":1740021359000,"heart_rate":59,"heart_rate_max":71,"heart_rate_min":59,"start_time":1740021300000},{"end_time":1740021419000,"heart_rate":62,"heart_rate_max":68,"heart_rate_min":62,"start_time":1740021360000},{"end_time":1740021479000,"heart_rate":60,"heart_rate_max":74,"heart_rate_min":60,"start_time":1740021420000},{"end_time":1740021539000,"heart_rate":60,"heart_rate_max":71,"heart_rate_min":60,"start_time":1740021480000},{"end_time":1740021599000,"heart_rate":65,"heart_rate_max":72,"heart_rate_min":65,"start_time":1740021540000},{"end_time":1740021659000,"heart_rate":64,"heart_rate_max":85,"heart_rate_min":64,"start_time":1740021600000},{"end_time":1740021719000,"heart_rate":59,"heart_rate_max":69,"heart_rate_min":59,"start_time":1740021660000},{"end_time":1740021779000,"heart_rate":61,"heart_rate_max":76,"heart_rate_min":61,"start_time":1740021720000},{"end_time":1740021839000,"heart_rate":59,"heart_rate_max":72,"heart_rate_min":59,"start_time":1740021780000},{"end_time":1740021899000,"heart_rate":61,"heart_rate_max":74,"heart_rate_min":61,"start_time":1740021840000},{"end_time":1740021959000,"heart_rate":61,"heart_rate_max":73,"heart_rate_min":61,"start_time":1740021900000},{"end_time":1740022019000,"heart_rate":59,"heart_rate_max":70,"heart_rate_min":59,"start_time":1740021960000},{"end_time":1740022079000,"heart_rate":62,"heart_rate_max":84,"heart_rate_min":62,"start_time":1740022020000},{"end_time":1740022139000,"heart_rate":59,"heart_rate_max":67,"heart_rate_min":59,"start_time":1740022080000},{"end_time":1740022199000,"heart_rate":60,"heart_rate_max":66,"heart_rate_min":60,"start_time":1740022140000},{"end_time":1740022259000,"heart_rate":57,"heart_rate_max":73,"heart_rate_min":57,"start_time":1740022200000},{"end_time":1740022319000,"heart_rate":58,"heart_rate_max":65,"heart_rate_min":58,"start_time":1740022260000},{"end_time":1740022379000,"heart_rate":58,"heart_rate_max":61,"heart_rate_min":58,"start_time":1740022320000},{"end_time":1740022439000,"heart_rate":59,"heart_rate_max":62,"heart_rate_min":59,"start_time":1740022380000},{"end_time":1740022499000,"heart_rate":61,"heart_rate_max":63,"heart_rate_min":61,"start_time":1740022440000},{"end_time":1740022559000,"heart_rate":59,"heart_rate_max":67,"heart_rate_min":59,"start_time":1740022500000},{"end_time":1740022619000,"heart_rate":59,"heart_rate_max":63,"heart_rate_min":59,"start_time":1740022560000},{"end_time":1740022679000,"heart_rate":59,"heart_rate_max":68,"heart_rate_min":59,"start_time":1740022620000},{"end_time":1740022739000,"heart_rate":60,"heart_rate_max":69,"heart_rate_min":60,"start_time":1740022680000},{"end_time":1740022799000,"heart_rate":58,"heart_rate_max":72,"heart_rate_min":58,"start_time":1740022740000},{"end_time":1740022859000,"heart_rate":59,"heart_rate_max":66,"heart_rate_min":59,"start_time":1740022800000},{"end_time":1740022919000,"heart_rate":62,"heart_rate_max":83,"heart_rate_min":62,"start_time":1740022860000},{"end_time":1740022979000,"heart_rate":62,"heart_rate_max":65,"heart_rate_min":62,"start_time":1740022920000},{"end_time":1740023039000,"heart_rate":62,"heart_rate_max":65,"heart_rate_min":62,"start_time":1740022980000},{"end_time":1740023099000,"heart_rate":62,"heart_rate_max":69,"heart_rate_min":62,"start_time":1740023040000},{"end_time":1740023159000,"heart_rate":62,"heart_rate_max":74,"heart_rate_min":62,"start_time":1740023100000},{"end_time":1740023219000,"heart_rate":61,"heart_rate_max":70,"heart_rate_min":61,"start_time":1740023160000},{"end_time":1740023279000,"heart_rate":61,"heart_rate_max":63,"heart_rate_min":61,"start_time":1740023220000},{"end_time":1740023339000,"heart_rate":61,"heart_rate_max":63,"heart_rate_min":61,"start_time":1740023280000},{"end_time":1740023399000,"heart_rate":62,"heart_rate_max":64,"heart_rate_min":62,"start_time":1740023340000},{"end_time":1740023459000,"heart_rate":62,"heart_rate_max":64,"heart_rate_min":62,"start_time":1740023400000},{"end_time":1740023519000,"heart_rate":62,"heart_rate_max":63,"heart_rate_min":62,"start_time":1740023460000},{"end_time":1740023579000,"heart_rate":62,"heart_rate_max":64,"heart_rate_min":62,"start_time":1740023520000},{"end_time":1740023639000,"heart_rate":63,"heart_rate_max":64,"heart_rate_min":63,"start_time":1740023580000},{"end_time":1740023699000,"heart_rate":63,"heart_rate_max":64,"heart_rate_min":63,"start_time":1740023640000},{"end_time":1740023759000,"heart_rate":62,"heart_rate_max":64,"heart_rate_min":62,"start_time":1740023700000},{"end_time":1740023819000,"heart_rate":63,"heart_rate_max":65,"heart_rate_min":63,"start_time":1740023760000},{"end_time":1740023879000,"heart_rate":62,"heart_rate_max":64,"heart_rate_min":62,"start_time":1740023820000},{"end_time":1740023939000,"heart_rate":62,"heart_rate_max":64,"heart_rate_min":62,"start_time":1740023880000}]